teachstack/__init__.py
teachstack-0.1.dist-info/LICENSE.txt
teachstack-0.1.dist-info/METADATA
teachstack-0.1.dist-info/WHEEL
teachstack-0.1.dist-info/top_level.txt
teachstack-0.1.dist-info/RECORD
